README.rst
setup.cfg
setup.py
brine/__init__.py
brine/__main__.py
brine/api.py
brine/archive.py
brine/build.py
brine/builder.py
brine/dataset.py
brine/dataset_manager.py
brine/download.py
brine/env.py
brine/exceptions.py
brine/info.py
brine/install.py
brine/iterator.py
brine/keras_generator.py
brine/ls.py
brine/push.py
brine/pytorch_dataset.py
brine/schema.py
brine/uninstall.py
brine/upload.py
brine/util.py
brine_io.egg-info/PKG-INFO
brine_io.egg-info/SOURCES.txt
brine_io.egg-info/dependency_links.txt
brine_io.egg-info/entry_points.txt
brine_io.egg-info/requires.txt
brine_io.egg-info/top_level.txt