Metadata-Version: 1.2
Name: brine-io
Version: 0.5.1
Summary: Dataset management for computer vision
Home-page: https://github.com/brine-io/brine
Author: David Ye
Author-email: david@brine.io
License: LICENSE
Download-URL: https://github.com/brine-io/brine/archive/0.5.1.tar.gz
Keywords: brine
Platform: UNKNOWN
Classifier: Development Status :: 4 - Beta
Classifier: License :: OSI Approved :: Apache Software License
Classifier: Programming Language :: Python :: 3.4
Classifier: Programming Language :: Python :: 3.5
Classifier: Programming Language :: Python :: 3.6
Requires-Python: >=3
